httpobs/__init__.py
httpobs/conf/__init__.py
httpobs/conf/amazon-rds.pem
httpobs/conf/hsts-preload.json
httpobs/conf/httpobs.conf
httpobs/scanner/__init__.py
httpobs/scanner/celeryconfig.py
httpobs/scanner/local.py
httpobs/scanner/main.py
httpobs/scanner/tasks.py
httpobs/scanner/utils.py
httpobs/scanner/analyzer/__init__.py
httpobs/scanner/analyzer/content.py
httpobs/scanner/analyzer/decorators.py
httpobs/scanner/analyzer/headers.py
httpobs/scanner/analyzer/misc.py
httpobs/scanner/analyzer/utils.py
httpobs/scanner/grader/__init__.py
httpobs/scanner/grader/grade.py
httpobs/scanner/retriever/__init__.py
httpobs/scanner/retriever/retriever.py
httpobs/scripts/httpobs-local-scan
httpobs/scripts/httpobs-scan-worker
httpobs/tests/__init__.py
httpobs/tests/utils.py
httpobs/tests/unittests/__init__.py
httpobs/tests/unittests/test_content.py
httpobs/tests/unittests/test_environ.py
httpobs/tests/unittests/test_grades.py
httpobs/tests/unittests/test_headers.py
httpobs/tests/unittests/test_misc.py
httpobs/tests/unittests/test_parse_http_equiv_headers.py
httpobs/tests/unittests/test_preload.py
httpobs/tests/unittests/test_retriever.py
httpobs/tests/unittests/test_sanitize_headers.py
httpobs/tests/unittests/test_valid_hostname.py
httpobs_alt_scanner-0.9.3.data/scripts/httpobs-local-scan
httpobs_alt_scanner-0.9.3.data/scripts/httpobs-scan-worker
httpobs_alt_scanner-0.9.3.dist-info/LICENSE
httpobs_alt_scanner-0.9.3.dist-info/METADATA
httpobs_alt_scanner-0.9.3.dist-info/WHEEL
httpobs_alt_scanner-0.9.3.dist-info/top_level.txt
httpobs_alt_scanner-0.9.3.dist-info/RECORD
