Metadata-Version: 2.1
Name: httpobs-alt-scanner
Version: 0.9.3
Summary: HTTP Observatory: a set of tests and tools to scan your website for basic web hygeine.
Home-page: https://github.com/mozilla/http-observatory
Author: April King
Author-email: april@mozilla.com
Classifier: Development Status :: 4 - Beta
Classifier: Environment :: Web Environment
Classifier: Framework :: Flask
Classifier: Intended Audience :: Developers
Classifier: Intended Audience :: System Administrators
Classifier: License :: OSI Approved :: Mozilla Public License 2.0 (MPL 2.0)
Classifier: Natural Language :: English
Classifier: Programming Language :: Python :: 3 :: Only
Classifier: Topic :: Internet :: WWW/HTTP :: HTTP Servers
Classifier: Topic :: Security
Classifier: Topic :: Software Development :: Quality Assurance
License-File: LICENSE
Requires-Dist: beautifulsoup4
Requires-Dist: celery
Requires-Dist: psutil
Requires-Dist: publicsuffixlist
Requires-Dist: requests
Requires-Dist: vine
